bdv/__init__.py
bdv/config.py
imglyb_bdv-0.1.0.dist-info/LICENSE.txt
imglyb_bdv-0.1.0.dist-info/METADATA
imglyb_bdv-0.1.0.dist-info/WHEEL
imglyb_bdv-0.1.0.dist-info/top_level.txt
imglyb_bdv-0.1.0.dist-info/RECORD
