Metadata-Version: 2.1
Name: imglyb-bdv
Version: 0.1.0
Summary: A python module adding BigDataViewer functions to imglyb.
Home-page: https://github.com/imglib/imglyb-bdv
Author: Philipp Hanslovsky, Curtis Rueden, Edward Evans, Mark Hiner
Author-email: ctrueden@wisc.edu
License: Simplified BSD License
Platform: UNKNOWN
Requires-Python: >=3
Requires-Dist: scyjava (>=1.3.0)
Requires-Dist: imglyb (>=2.0.0)
